mcp_kandinsky/__init__.py
mcp_kandinsky/__main__.py
mcp_kandinsky/kandinsky_api.py
mcp_kandinsky/server.py
mcp_kandinsky-0.2.0.dist-info/licenses/LICENSE
mcp_kandinsky-0.2.0.dist-info/METADATA
mcp_kandinsky-0.2.0.dist-info/WHEEL
mcp_kandinsky-0.2.0.dist-info/entry_points.txt
mcp_kandinsky-0.2.0.dist-info/top_level.txt
mcp_kandinsky-0.2.0.dist-info/RECORD
