Metadata-Version: 2.4
Name: mcp_kandinsky
Version: 0.2.0
Summary: MCP сервер для генерации изображений через Kandinsky API
Author-email: Sergei Trashchenkov <trashchenkov@gmail.com>
License: MIT
Project-URL: Homepage, https://github.com/ai-forever/mcp_kandinsky
Project-URL: Repository, https://github.com/ai-forever/mcp_kandinsky
Requires-Python: >=3.9
License-File: LICENSE
Requires-Dist: httpx>=0.28.1
Requires-Dist: mcp[cli]>=1.6.0
Requires-Dist: numpy>=1.26.0
Dynamic: license-file
